Py_Rate-0.6.1.data/scripts/gdal_calc_local.py
Py_Rate-0.6.1.data/scripts/plot_ifgs.py
pyrate/__init__.py
pyrate/configuration.py
pyrate/constants.py
pyrate/conv2tif.py
pyrate/correct.py
pyrate/default_parameters.py
pyrate/main.py
pyrate/merge.py
pyrate/prepifg.py
pyrate/core/__init__.py
pyrate/core/algorithm.py
pyrate/core/aps.py
pyrate/core/covariance.py
pyrate/core/dem_error.py
pyrate/core/gamma.py
pyrate/core/gdal_python.py
pyrate/core/geometry.py
pyrate/core/ifgconstants.py
pyrate/core/logger.py
pyrate/core/mpiops.py
pyrate/core/mst.py
pyrate/core/orbital.py
pyrate/core/prepifg_helper.py
pyrate/core/ref_phs_est.py
pyrate/core/refpixel.py
pyrate/core/roipac.py
pyrate/core/shared.py
pyrate/core/stack.py
pyrate/core/timeseries.py
pyrate/core/phase_closure/__init__.py
pyrate/core/phase_closure/closure_check.py
pyrate/core/phase_closure/collect_loops.py
pyrate/core/phase_closure/correct_phase.py
pyrate/core/phase_closure/mst_closure.py
pyrate/core/phase_closure/plot_closure.py
pyrate/core/phase_closure/sum_closure.py
tests/__init__.py
tests/common.py
tests/conftest.py
tests/test_algorithm.py
tests/test_aps.py
tests/test_constants.py
tests/test_conv2tif.py
tests/test_correct.py
tests/test_covariance.py
tests/test_dem_error.py
tests/test_gamma.py
tests/test_gamma_vs_roipac.py
tests/test_gdal_python.py
tests/test_geometry.py
tests/test_merge.py
tests/test_mpi.py
tests/test_mpi_vs_multiprocess_vs_single_process.py
tests/test_mst.py
tests/test_orbital.py
tests/test_prepifg.py
tests/test_prepifg_system_vs_python.py
tests/test_pyrate.py
tests/test_ref_phs_est.py
tests/test_refpixel.py
tests/test_roipac.py
tests/test_shared.py
tests/test_stackrate.py
tests/test_system.py
tests/test_timeseries.py
tests/phase_closure/__init__.py
tests/phase_closure/common.py
tests/phase_closure/conftest.py
tests/phase_closure/test_closure_check.py
tests/phase_closure/test_collect_loops.py
tests/phase_closure/test_mst_closure.py
tests/phase_closure/test_plot_closure.py
Py_Rate-0.6.1.dist-info/LICENSE
Py_Rate-0.6.1.dist-info/METADATA
Py_Rate-0.6.1.dist-info/WHEEL
Py_Rate-0.6.1.dist-info/entry_points.txt
Py_Rate-0.6.1.dist-info/top_level.txt
Py_Rate-0.6.1.dist-info/RECORD
