Metadata-Version: 2.1
Name: Py-Rate
Version: 0.6.1
Summary: A Python tool for estimating velocity and cumulative displacement time-series from Interferometric Synthetic Aperture Radar (InSAR) data.
Home-page: https://github.com/GeoscienceAustralia/PyRate
Author: Geoscience Australia InSAR team
Author-email: insar@ga.gov.au
License: Apache Software License 2.0
Download-URL: https://github.com/GeoscienceAustralia/PyRate/archive/0.6.1.tar.gz
Keywords: PyRate,Python,InSAR,Geodesy,Remote Sensing,Image Processing
Platform: UNKNOWN
Classifier: Development Status :: 4 - Beta
Classifier: Operating System :: POSIX
Classifier: License :: OSI Approved :: Apache Software License
Classifier: Natural Language :: English
Classifier: Programming Language :: Python
Classifier: Programming Language :: Python :: 3
Classifier: Programming Language :: Python :: 3.7
Classifier: Programming Language :: Python :: 3.8
Classifier: Programming Language :: Python :: 3.9
Classifier: Intended Audience :: Science/Research
Classifier: Intended Audience :: Developers
Classifier: Topic :: Software Development :: Libraries :: Python Modules
Classifier: Topic :: Scientific/Engineering :: Information Analysis
Requires-Dist: GDAL (==3.0.4)
Requires-Dist: joblib (==1.0.0)
Requires-Dist: mpi4py (==3.0.3)
Requires-Dist: networkx (==2.5)
Requires-Dist: numpy (==1.19.4)
Requires-Dist: pyproj (==3.0.0)
Requires-Dist: scipy (==1.5.4)
Requires-Dist: numexpr (==2.7.2)
Requires-Dist: nptyping (==1.4.0)
Provides-Extra: dev
Requires-Dist: ghp-import (==0.5.5) ; extra == 'dev'
Requires-Dist: sphinx (==3.0.3) ; extra == 'dev'
Requires-Dist: sphinx-rtd-theme (==0.4.3) ; extra == 'dev'
Requires-Dist: sphinxcontrib-programoutput (==0.16) ; extra == 'dev'
Requires-Dist: recommonmark (==0.6.0) ; extra == 'dev'
Requires-Dist: m2r2 ; extra == 'dev'
Requires-Dist: mpi4py (==3.0.3) ; extra == 'dev'
Requires-Dist: matplotlib ; extra == 'dev'
Requires-Dist: ipython ; extra == 'dev'
Requires-Dist: setuptools ; extra == 'dev'
Requires-Dist: twine ; extra == 'dev'
Requires-Dist: wheel ; extra == 'dev'
Requires-Dist: pylint ; extra == 'dev'
Requires-Dist: pytest ; extra == 'dev'
